itads_test_package/__init__.py
itads_test_package/gitads_test.py
gitads_test_package-0.0.4.dist-info/METADATA
gitads_test_package-0.0.4.dist-info/WHEEL
gitads_test_package-0.0.4.dist-info/top_level.txt
gitads_test_package-0.0.4.dist-info/RECORD
